ksprepro/__init__.py
ksprepro/core.py
ksprepro-0.2.dist-info/licenses/LICENSE
ksprepro-0.2.dist-info/METADATA
ksprepro-0.2.dist-info/WHEEL
ksprepro-0.2.dist-info/top_level.txt
ksprepro-0.2.dist-info/RECORD
